LICENSE
README
setup.py
src/CryptoPlus/Protocol.py
src/CryptoPlus/PublicKey.py
src/CryptoPlus/__init__.py
src/CryptoPlus/testvectors.py
src/CryptoPlus/Cipher/AES.py
src/CryptoPlus/Cipher/ARC2.py
src/CryptoPlus/Cipher/Blowfish.py
src/CryptoPlus/Cipher/CAST.py
src/CryptoPlus/Cipher/DES.py
src/CryptoPlus/Cipher/DES3.py
src/CryptoPlus/Cipher/IDEA.py
src/CryptoPlus/Cipher/RC5.py
src/CryptoPlus/Cipher/__init__.py
src/CryptoPlus/Cipher/blockcipher.py
src/CryptoPlus/Cipher/pyDes.py
src/CryptoPlus/Cipher/pyblowfish.py
src/CryptoPlus/Cipher/pypresent.py
src/CryptoPlus/Cipher/pyserpent.py
src/CryptoPlus/Cipher/python_AES.py
src/CryptoPlus/Cipher/python_Blowfish.py
src/CryptoPlus/Cipher/python_DES.py
src/CryptoPlus/Cipher/python_DES3.py
src/CryptoPlus/Cipher/python_PRESENT.py
src/CryptoPlus/Cipher/python_Rijndael.py
src/CryptoPlus/Cipher/python_Serpent.py
src/CryptoPlus/Cipher/python_Twofish.py
src/CryptoPlus/Cipher/pytwofish.py
src/CryptoPlus/Cipher/rijndael.py
src/CryptoPlus/Hash/RIPEMD.py
src/CryptoPlus/Hash/__init__.py
src/CryptoPlus/Hash/pymd5.py
src/CryptoPlus/Hash/pypbkdf2.py
src/CryptoPlus/Hash/pyradiogatun.py
src/CryptoPlus/Hash/pysha.py
src/CryptoPlus/Hash/pysha224.py
src/CryptoPlus/Hash/pysha256.py
src/CryptoPlus/Hash/pysha384.py
src/CryptoPlus/Hash/pysha512.py
src/CryptoPlus/Hash/python_MD5.py
src/CryptoPlus/Hash/python_PBKDF2.py
src/CryptoPlus/Hash/python_RadioGatun.py
src/CryptoPlus/Hash/python_SHA.py
src/CryptoPlus/Hash/python_SHA224.py
src/CryptoPlus/Hash/python_SHA256.py
src/CryptoPlus/Hash/python_SHA384.py
src/CryptoPlus/Hash/python_SHA512.py
src/CryptoPlus/Hash/python_whirlpool.py
src/CryptoPlus/Hash/pywhirlpool.py
src/CryptoPlus/Random/Fortuna.py
src/CryptoPlus/Random/OSRNG.py
src/CryptoPlus/Random/__init__.py
src/CryptoPlus/SelfTest/__init__.py
src/CryptoPlus/SelfTest/st_common.py
src/CryptoPlus/SelfTest/Cipher/__init__.py
src/CryptoPlus/SelfTest/Cipher/common.py
src/CryptoPlus/SelfTest/Cipher/test_AES.py
src/CryptoPlus/SelfTest/Cipher/test_ARC2.py
src/CryptoPlus_new.egg-info/PKG-INFO
src/CryptoPlus_new.egg-info/SOURCES.txt
src/CryptoPlus_new.egg-info/dependency_links.txt
src/CryptoPlus_new.egg-info/requires.txt
src/CryptoPlus_new.egg-info/top_level.txt
